cel_in_py/#__init__.py#
cel_in_py/__init__.py
cel_in_py/cel_in_py.py
cel_in_py/cli.py
cel_in_py/runtime.py
cel_in_py/runtime.py~
cel_in_py/runtine.py~
cel_in_py/visitor_interp.py
cel_in_py/parser/#CELParser.py#
cel_in_py/parser/CEL.interp
cel_in_py/parser/CEL.tokens
cel_in_py/parser/CELLexer.interp
cel_in_py/parser/CELLexer.py
cel_in_py/parser/CELLexer.tokens
cel_in_py/parser/CELListener.py
cel_in_py/parser/CELParser.py
cel_in_py/parser/CELVisitor.py
cel_in_py/parser/__init__.py
cel_python3-0.0.2.dist-info/LICENSE
cel_python3-0.0.2.dist-info/METADATA
cel_python3-0.0.2.dist-info/WHEEL
cel_python3-0.0.2.dist-info/top_level.txt
cel_python3-0.0.2.dist-info/RECORD
