Metadata-Version: 2.1
Name: cel_python3
Version: 0.0.2
Summary: Parser and evaluator for CEL in Python using Antlr
Author-email: yottanami <b.khanbeigi@gresb.com>
Maintainer-email: yottanami <b.khanbeigi@gresb.com>
License: GNU General Public License v3
Project-URL: bugs, https://github.com/gresb/cel_py/issues
Project-URL: homepage, https://github.com/gresb/cel_py
Classifier: Programming Language :: Python :: 3
Classifier: Operating System :: OS Independent
License-File: LICENSE
Requires-Dist: typer
Provides-Extra: dev
Requires-Dist: coverage ; extra == 'dev'
Requires-Dist: mypy ; extra == 'dev'
Requires-Dist: pytest ; extra == 'dev'
Requires-Dist: ruff ; extra == 'dev'
